{"timestamp": 1770620809.666629, "objects": [{"id": "Green_Dice_0", "type": "dice", "properties": {"color": "green"}, "transform": {"position": {"x": 90.9, "y": 10, "z": 64.7}, "rotation": {"x": 0, "y": 45, "z": 0}, "scale": {"x": 1, "y": 1, "z": 1}}}, {"id": "Orange_Dice_0", "type": "dice", "properties": {"color": "orange"}, "transform": {"position": {"x": 84.7, "y": 10, "z": 90.5}, "rotation": {"x": 0, "y": 45, "z": 0}, "scale": {"x": 1, "y": 1, "z": 1}}}, {"id": "Pink_Dice_0", "type": "dice", "properties": {"color": "pink"}, "transform": {"position": {"x": 75.5, "y": 10, "z": 44.5}, "rotation": {"x": 0, "y": 15, "z": 0}, "scale": {"x": 1, "y": 1, "z": 1}}}, {"id": "Yellow_Dice_0", "type": "dice", "properties": {"color": "yellow"}, "transform": {"position": {"x": 69.5, "y": 10, "z": 103.9}, "rotation": {"x": 0, "y": 15, "z": 0}, "scale": {"x": 1, "y": 1, "z": 1}}}, {"id": "Blue_Dice_0", "type": "dice", "properties": {"color": "blue"}, "transform": {"position": {"x": 67.0, "y": 10, "z": 72.6}, "rotation": {"x": 0, "y": 45, "z": 0}, "scale": {"x": 1, "y": 1, "z": 1}}}, {"id": "Red_Dice_0", "type": "dice", "properties": {"color": "red"}, "transform": {"position": {"x": 58.5, "y": 10, "z": 45.4}, "rotation": {"x": 0, "y": 45, "z": 0}, "scale": {"x": 1, "y": 1, "z": 1}}}]}